lp1379-0.1.0.dist-info/METADATA
lp1379-0.1.0.dist-info/WHEEL
lp1379.libs/libgcc_s-0366c7ba.so.1
lp1379/__init__.py
lp1379/lp1379.pypy311-pp73-arm-linux-gnu.so
lp1379-0.1.0.dist-info/RECORD
