Metadata-Version: 2.4
Name: lp1379
Version: 0.1.0
Summary: A common framework to analyse multi-modal single-cell data.
Author-email: Ward Deboutte <w@rddeboutte.com>
Requires-Python: >3.10
Project-URL: Homepage, https://github.com/WardDeb/listening_post_1379
Project-URL: Repository, https://github.com/WardDeb/listening_post_1379
